AUTHORS.rst
CONTRIBUTING.rst
HISTORY.rst
LICENSE
README.rst
pytemplator/__init__.py
pytemplator/cli.py
pytemplator/constants.py
pytemplator/exceptions.py
pytemplator/pytemplator.py
pytemplator/utils.py
pytemplator-0.1.0a2.dist-info/entry_points.txt
pytemplator-0.1.0a2.dist-info/LICENSE
pytemplator-0.1.0a2.dist-info/WHEEL
pytemplator-0.1.0a2.dist-info/METADATA
pytemplator-0.1.0a2.dist-info/RECORD
