Metadata-Version: 2.1
Name: pytemplator
Version: 0.1.0a2
Summary: Pytemplator aims to streamline the creation of dynamic templates. It is inspired from the excellent CookieCutter package but offers more flexibility.
License: Apache-2.0
Keywords: packaging,template,templating,boilerplate,cookiecutter
Author: Arnaud Blois
Author-email: hi@arnaudblois.com
Requires-Python: >=3.10,<4.0
Classifier: Development Status :: 3 - Alpha
Classifier: License :: OSI Approved :: Apache Software License
Classifier: Programming Language :: Python :: 3
Classifier: Programming Language :: Python :: 3.10
Classifier: Topic :: Software Development :: Code Generators
Classifier: Topic :: Utilities
Requires-Dist: Jinja2 (>=3.0.3,<4.0.0)
Requires-Dist: PyYAML (>=6.0,<7.0)
Requires-Dist: loguru (>=0.6.0,<0.7.0)
